antimony_combinations/__init__.py
antimony_combinations/antimony_combinations.py
AntimonyCombinations-0.0.3.dist-info/LICENCE
AntimonyCombinations-0.0.3.dist-info/METADATA
AntimonyCombinations-0.0.3.dist-info/WHEEL
AntimonyCombinations-0.0.3.dist-info/top_level.txt
AntimonyCombinations-0.0.3.dist-info/RECORD
