Metadata-Version: 2.1
Name: AntimonyCombinations
Version: 0.0.3
Summary: UNKNOWN
Home-page: https://github.com/CiaranWelsh/AntimonyCombinations
Author: Ciaran Welsh
Author-email: ciaran.welsh@newcastle.ac.uk
License: MIT
Keywords: SBML,antimony,tellurium,model selection,combinations,model merging
Platform: UNKNOWN
Requires-Dist: tellurium
Requires-Dist: pycotools3
Requires-Dist: pandas
Requires-Dist: numpy
